<?xml version="1.0" encoding="utf-8"?>
<clothing-items>
 <clothing>
  <id>
   873159732
  </id>
  <name>
   Brooks Pants C-1090
  </name>
  <category>
   Pants
  </category>
  <size>
   S
  </size>
  <color>
   Фиолетовый
  </color>
  <material>
   Шерсть
  </material>
  <price>
   383691
  </price>
  <rating>
   1.39
  </rating>
  <reviews>
   313066
  </reviews>
  <new>
   +
  </new>
  <exclusive>
   yes
  </exclusive>
  <sporty>
   no
  </sporty>
 </clothing>
 <clothing>
  <id>
   276207708
  </id>
  <name>
   Reebok Handbags M-1359
  </name>
  <category>
   Handbags
  </category>
  <size>
   XXL
  </size>
  <color>
   Синий
  </color>
  <material>
   Нейлон
  </material>
  <price>
   489817
  </price>
  <rating>
   2.2
  </rating>
  <reviews>
   800416
  </reviews>
  <new>
   +
  </new>
 </clothing>
 <clothing>
  <id>
   723757774
  </id>
  <name>
   Fila Shoes R-1491
  </name>
  <category>
   Shoes
  </category>
  <size>
   L
  </size>
  <color>
   Оранжевый
  </color>
  <material>
   Лен
  </material>
  <price>
   524930
  </price>
  <rating>
   3.05
  </rating>
  <reviews>
   340917
  </reviews>
  <new>
   -
  </new>
 </clothing>
 <clothing>
  <id>
   283519501
  </id>
  <name>
   Ellesse Umbrellas D-6300
  </name>
  <category>
   Umbrellas
  </category>
  <size>
   L
  </size>
  <color>
   Красный
  </color>
  <material>
   Кожа
  </material>
  <price>
   744519
  </price>
  <rating>
   3.91
  </rating>
  <reviews>
   144338
  </reviews>
  <new>
   -
  </new>
  <exclusive>
   yes
  </exclusive>
  <sporty>
   yes
  </sporty>
 </clothing>
 <clothing>
  <id>
   335629310
  </id>
  <name>
   Under Armour Jeans J-2839
  </name>
  <category>
   Jeans
  </category>
  <size>
   S
  </size>
  <color>
   Оранжевый
  </color>
  <material>
   Хлопок
  </material>
  <price>
   634945
  </price>
  <rating>
   4.78
  </rating>
  <reviews>
   112997
  </reviews>
  <exclusive>
   yes
  </exclusive>
  <sporty>
   no
  </sporty>
 </clothing>
 <clothing>
  <id>
   296116973
  </id>
  <name>
   Vans Belts Y-4761
  </name>
  <category>
   Belts
  </category>
  <size>
   L
  </size>
  <color>
   Фиолетовый
  </color>
  <material>
   Лен
  </material>
  <price>
   941971
  </price>
  <rating>
   4.97
  </rating>
  <reviews>
   719694
  </reviews>
  <exclusive>
   no
  </exclusive>
  <sporty>
   no
  </sporty>
 </clothing>
 <clothing>
  <id>
   583849726
  </id>
  <name>
   Under Armour Jacket O-1912
  </name>
  <category>
   Jacket
  </category>
  <size>
   L
  </size>
  <color>
   Фиолетовый
  </color>
  <material>
   Шелк
  </material>
  <price>
   441275
  </price>
  <rating>
   2.89
  </rating>
  <reviews>
   620591
  </reviews>
  <exclusive>
   yes
  </exclusive>
  <sporty>
   no
  </sporty>
 </clothing>
 <clothing>
  <id>
   430155070
  </id>
  <name>
   Adidas Umbrellas P-5317
  </name>
  <category>
   Umbrellas
  </category>
  <size>
   S
  </size>
  <color>
   Зеленый
  </color>
  <material>
   Кожа
  </material>
  <price>
   211188
  </price>
  <rating>
   1.64
  </rating>
  <reviews>
   694417
  </reviews>
  <new>
   -
  </new>
 </clothing>
 <clothing>
  <id>
   173828913
  </id>
  <name>
   Fila Gloves H-9015
  </name>
  <category>
   Gloves
  </category>
  <size>
   L
  </size>
  <color>
   Фиолетовый
  </color>
  <material>
   Шерсть
  </material>
  <price>
   112486
  </price>
  <rating>
   4.39
  </rating>
  <reviews>
   253713
  </reviews>
  <new>
   +
  </new>
  <exclusive>
   no
  </exclusive>
  <sporty>
   yes
  </sporty>
 </clothing>
 <clothing>
  <id>
   217622930
  </id>
  <name>
   Ellesse Gloves F-2443
  </name>
  <category>
   Gloves
  </category>
  <size>
   S
  </size>
  <color>
   Желтый
  </color>
  <material>
   Нейлон
  </material>
  <price>
   401774
  </price>
  <rating>
   3.27
  </rating>
  <reviews>
   419689
  </reviews>
  <sporty>
   no
  </sporty>
 </clothing>
 <clothing>
  <id>
   900668504
  </id>
  <name>
   New Balance T-shirt Z-1033
  </name>
  <category>
   T-shirt
  </category>
  <size>
   L
  </size>
  <color>
   Голубой
  </color>
  <material>
   Вискоза
  </material>
  <price>
   313508
  </price>
  <rating>
   2.53
  </rating>
  <reviews>
   293286
  </reviews>
 </clothing>
 <clothing>
  <id>
   707690332
  </id>
  <name>
   Under Armour Blouse L-6718
  </name>
  <category>
   Blouse
  </category>
  <size>
   XXL
  </size>
  <color>
   Красный
  </color>
  <material>
   Полиэстер
  </material>
  <price>
   106818
  </price>
  <rating>
   2.36
  </rating>
  <reviews>
   720676
  </reviews>
  <new>
   -
  </new>
  <exclusive>
   no
  </exclusive>
  <sporty>
   yes
  </sporty>
 </clothing>
 <clothing>
  <id>
   932418752
  </id>
  <name>
   Reebok Umbrellas F-7436
  </name>
  <category>
   Umbrellas
  </category>
  <size>
   S
  </size>
  <color>
   Голубой
  </color>
  <material>
   Хлопок
  </material>
  <price>
   911060
  </price>
  <rating>
   1.24
  </rating>
  <reviews>
   322344
  </reviews>
  <new>
   -
  </new>
  <exclusive>
   no
  </exclusive>
 </clothing>
 <clothing>
  <id>
   779221574
  </id>
  <name>
   New Balance Jeans D-6439
  </name>
  <category>
   Jeans
  </category>
  <size>
   S
  </size>
  <color>
   Желтый
  </color>
  <material>
   Шелк
  </material>
  <price>
   762831
  </price>
  <rating>
   2.79
  </rating>
  <reviews>
   982472
  </reviews>
 </clothing>
 <clothing>
  <id>
   799912235
  </id>
  <name>
   Fila Socks D-4588
  </name>
  <category>
   Socks
  </category>
  <size>
   XL
  </size>
  <color>
   Желтый
  </color>
  <material>
   Кожа
  </material>
  <price>
   314359
  </price>
  <rating>
   3.95
  </rating>
  <reviews>
   33941
  </reviews>
  <new>
   -
  </new>
  <sporty>
   yes
  </sporty>
 </clothing>
 <clothing>
  <id>
   538864623
  </id>
  <name>
   Under Armour Hat R-7569
  </name>
  <category>
   Hat
  </category>
  <size>
   S
  </size>
  <color>
   Синий
  </color>
  <material>
   Шелк
  </material>
  <price>
   487814
  </price>
  <rating>
   4.88
  </rating>
  <reviews>
   700441
  </reviews>
  <new>
   -
  </new>
  <sporty>
   yes
  </sporty>
 </clothing>
 <clothing>
  <id>
   300759927
  </id>
  <name>
   Converse Gloves I-3447
  </name>
  <category>
   Gloves
  </category>
  <size>
   XXL
  </size>
  <color>
   Синий
  </color>
  <material>
   Лен
  </material>
  <price>
   880016
  </price>
  <rating>
   3.74
  </rating>
  <reviews>
   468622
  </reviews>
 </clothing>
 <clothing>
  <id>
   131136442
  </id>
  <name>
   Lacoste Dress I-4215
  </name>
  <category>
   Dress
  </category>
  <size>
   S
  </size>
  <color>
   Голубой
  </color>
  <material>
   Кожа
  </material>
  <price>
   233643
  </price>
  <rating>
   1.13
  </rating>
  <reviews>
   187936
  </reviews>
  <new>
   -
  </new>
  <sporty>
   no
  </sporty>
 </clothing>
 <clothing>
  <id>
   619827718
  </id>
  <name>
   Puma Socks S-3818
  </name>
  <category>
   Socks
  </category>
  <size>
   M
  </size>
  <color>
   Желтый
  </color>
  <material>
   Лен
  </material>
  <price>
   392766
  </price>
  <rating>
   4.77
  </rating>
  <reviews>
   141781
  </reviews>
  <exclusive>
   yes
  </exclusive>
 </clothing>
 <clothing>
  <id>
   275894591
  </id>
  <name>
   Ellesse Shirt K-1325
  </name>
  <category>
   Shirt
  </category>
  <size>
   XL
  </size>
  <color>
   Желтый
  </color>
  <material>
   Шерсть
  </material>
  <price>
   925599
  </price>
  <rating>
   2.44
  </rating>
  <reviews>
   515134
  </reviews>
 </clothing>
 <clothing>
  <id>
   953868010
  </id>
  <name>
   Under Armour T-shirt Z-5600
  </name>
  <category>
   T-shirt
  </category>
  <size>
   M
  </size>
  <color>
   Оранжевый
  </color>
  <material>
   Шерсть
  </material>
  <price>
   374458
  </price>
  <rating>
   3.47
  </rating>
  <reviews>
   611232
  </reviews>
  <new>
   -
  </new>
  <exclusive>
   no
  </exclusive>
  <sporty>
   yes
  </sporty>
 </clothing>
 <clothing>
  <id>
   445890886
  </id>
  <name>
   Nike Umbrellas U-1161
  </name>
  <category>
   Umbrellas
  </category>
  <size>
   M
  </size>
  <color>
   Синий
  </color>
  <material>
   Нейлон
  </material>
  <price>
   885174
  </price>
  <rating>
   3.88
  </rating>
  <reviews>
   76593
  </reviews>
  <exclusive>
   no
  </exclusive>
  <sporty>
   yes
  </sporty>
 </clothing>
 <clothing>
  <id>
   589732131
  </id>
  <name>
   Fila Shoes A-9517
  </name>
  <category>
   Shoes
  </category>
  <size>
   M
  </size>
  <color>
   Красный
  </color>
  <material>
   Полиэстер
  </material>
  <price>
   160248
  </price>
  <rating>
   4.12
  </rating>
  <reviews>
   560784
  </reviews>
  <new>
   +
  </new>
  <sporty>
   yes
  </sporty>
 </clothing>
 <clothing>
  <id>
   387510641
  </id>
  <name>
   Nike Sweater T-4931
  </name>
  <category>
   Sweater
  </category>
  <size>
   XL
  </size>
  <color>
   Зеленый
  </color>
  <material>
   Полиэстер
  </material>
  <price>
   730055
  </price>
  <rating>
   4.72
  </rating>
  <reviews>
   477251
  </reviews>
  <exclusive>
   no
  </exclusive>
  <sporty>
   no
  </sporty>
 </clothing>
 <clothing>
  <id>
   190625900
  </id>
  <name>
   Ellesse Shoes N-2464
  </name>
  <category>
   Shoes
  </category>
  <size>
   XL
  </size>
  <color>
   Оранжевый
  </color>
  <material>
   Лен
  </material>
  <price>
   216199
  </price>
  <rating>
   3.81
  </rating>
  <reviews>
   709069
  </reviews>
  <new>
   +
  </new>
  <exclusive>
   no
  </exclusive>
  <sporty>
   yes
  </sporty>
 </clothing>
 <clothing>
  <id>
   267352655
  </id>
  <name>
   Puma Skirt T-5652
  </name>
  <category>
   Skirt
  </category>
  <size>
   XXL
  </size>
  <color>
   Желтый
  </color>
  <material>
   Шелк
  </material>
  <price>
   867115
  </price>
  <rating>
   4.35
  </rating>
  <reviews>
   452291
  </reviews>
  <new>
   +
  </new>
  <exclusive>
   no
  </exclusive>
 </clothing>
 <clothing>
  <id>
   597615285
  </id>
  <name>
   Reebok Blouse F-8587
  </name>
  <category>
   Blouse
  </category>
  <size>
   L
  </size>
  <color>
   Синий
  </color>
  <material>
   Вискоза
  </material>
  <price>
   745753
  </price>
  <rating>
   4.92
  </rating>
  <reviews>
   979376
  </reviews>
  <sporty>
   no
  </sporty>
 </clothing>
 <clothing>
  <id>
   801292435
  </id>
  <name>
   Converse Umbrellas R-5196
  </name>
  <category>
   Umbrellas
  </category>
  <size>
   XL
  </size>
  <color>
   Желтый
  </color>
  <material>
   Нейлон
  </material>
  <price>
   168917
  </price>
  <rating>
   1.3
  </rating>
  <reviews>
   998710
  </reviews>
  <new>
   +
  </new>
  <sporty>
   no
  </sporty>
 </clothing>
 <clothing>
  <id>
   654654511
  </id>
  <name>
   Fila Umbrellas S-4583
  </name>
  <category>
   Umbrellas
  </category>
  <size>
   XXL
  </size>
  <color>
   Оранжевый
  </color>
  <material>
   Шерсть
  </material>
  <price>
   929116
  </price>
  <rating>
   3.62
  </rating>
  <reviews>
   19249
  </reviews>
  <new>
   -
  </new>
  <exclusive>
   no
  </exclusive>
 </clothing>
 <clothing>
  <id>
   380999066
  </id>
  <name>
   Reebok Gloves P-6467
  </name>
  <category>
   Gloves
  </category>
  <size>
   S
  </size>
  <color>
   Зеленый
  </color>
  <material>
   Вискоза
  </material>
  <price>
   803316
  </price>
  <rating>
   3.7
  </rating>
  <reviews>
   610832
  </reviews>
  <new>
   -
  </new>
  <sporty>
   yes
  </sporty>
 </clothing>
 <clothing>
  <id>
   913211232
  </id>
  <name>
   Converse Socks M-9392
  </name>
  <category>
   Socks
  </category>
  <size>
   S
  </size>
  <color>
   Голубой
  </color>
  <material>
   Кожа
  </material>
  <price>
   349213
  </price>
  <rating>
   4.43
  </rating>
  <reviews>
   818741
  </reviews>
  <exclusive>
   no
  </exclusive>
 </clothing>
 <clothing>
  <id>
   410779451
  </id>
  <name>
   PleinSport Belts F-1514
  </name>
  <category>
   Belts
  </category>
  <size>
   L
  </size>
  <color>
   Голубой
  </color>
  <material>
   Лен
  </material>
  <price>
   820071
  </price>
  <rating>
   4.35
  </rating>
  <reviews>
   131423
  </reviews>
  <exclusive>
   yes
  </exclusive>
 </clothing>
 <clothing>
  <id>
   186479169
  </id>
  <name>
   PleinSport Sweater Y-6228
  </name>
  <category>
   Sweater
  </category>
  <size>
   XL
  </size>
  <color>
   Синий
  </color>
  <material>
   Хлопок
  </material>
  <price>
   850278
  </price>
  <rating>
   1.46
  </rating>
  <reviews>
   717162
  </reviews>
  <new>
   -
  </new>
  <exclusive>
   no
  </exclusive>
 </clothing>
 <clothing>
  <id>
   477956080
  </id>
  <name>
   Vans T-shirt P-3608
  </name>
  <category>
   T-shirt
  </category>
  <size>
   S
  </size>
  <color>
   Оранжевый
  </color>
  <material>
   Шерсть
  </material>
  <price>
   568071
  </price>
  <rating>
   3.49
  </rating>
  <reviews>
   983024
  </reviews>
  <exclusive>
   yes
  </exclusive>
 </clothing>
 <clothing>
  <id>
   299696522
  </id>
  <name>
   Ellesse Umbrellas P-1364
  </name>
  <category>
   Umbrellas
  </category>
  <size>
   XXL
  </size>
  <color>
   Голубой
  </color>
  <material>
   Вискоза
  </material>
  <price>
   383584
  </price>
  <rating>
   4.98
  </rating>
  <reviews>
   815662
  </reviews>
  <exclusive>
   no
  </exclusive>
  <sporty>
   no
  </sporty>
 </clothing>
 <clothing>
  <id>
   208201680
  </id>
  <name>
   Brooks Hat N-5669
  </name>
  <category>
   Hat
  </category>
  <size>
   XL
  </size>
  <color>
   Голубой
  </color>
  <material>
   Шелк
  </material>
  <price>
   113299
  </price>
  <rating>
   3.52
  </rating>
  <reviews>
   448825
  </reviews>
  <new>
   +
  </new>
  <exclusive>
   no
  </exclusive>
  <sporty>
   no
  </sporty>
 </clothing>
 <clothing>
  <id>
   827612229
  </id>
  <name>
   Asics Belts P-8720
  </name>
  <category>
   Belts
  </category>
  <size>
   S
  </size>
  <color>
   Оранжевый
  </color>
  <material>
   Нейлон
  </material>
  <price>
   368420
  </price>
  <rating>
   3.9
  </rating>
  <reviews>
   243390
  </reviews>
  <new>
   -
  </new>
  <sporty>
   no
  </sporty>
 </clothing>
 <clothing>
  <id>
   861284627
  </id>
  <name>
   Asics Belts V-4085
  </name>
  <category>
   Belts
  </category>
  <size>
   XL
  </size>
  <color>
   Красный
  </color>
  <material>
   Лен
  </material>
  <price>
   804049
  </price>
  <rating>
   2.84
  </rating>
  <reviews>
   425638
  </reviews>
  <sporty>
   yes
  </sporty>
 </clothing>
 <clothing>
  <id>
   510018522
  </id>
  <name>
   Addidas Handbags M-7328
  </name>
  <category>
   Handbags
  </category>
  <size>
   XXL
  </size>
  <color>
   Красный
  </color>
  <material>
   Вискоза
  </material>
  <price>
   838355
  </price>
  <rating>
   4.58
  </rating>
  <reviews>
   849641
  </reviews>
  <sporty>
   no
  </sporty>
 </clothing>
</clothing-items>
