<?xml version="1.0" encoding="utf-8"?>
<clothing-items>
 <clothing>
  <id>
   512388290
  </id>
  <name>
   Fila Shirt Y-7279
  </name>
  <category>
   Shirt
  </category>
  <size>
   L
  </size>
  <color>
   Красный
  </color>
  <material>
   Кожа
  </material>
  <price>
   977198
  </price>
  <rating>
   1.94
  </rating>
  <reviews>
   53539
  </reviews>
  <new>
   +
  </new>
  <exclusive>
   no
  </exclusive>
  <sporty>
   no
  </sporty>
 </clothing>
 <clothing>
  <id>
   516582224
  </id>
  <name>
   Under Armour Sweater Y-4103
  </name>
  <category>
   Sweater
  </category>
  <size>
   L
  </size>
  <color>
   Оранжевый
  </color>
  <material>
   Лен
  </material>
  <price>
   744557
  </price>
  <rating>
   2.9
  </rating>
  <reviews>
   889739
  </reviews>
  <new>
   +
  </new>
  <exclusive>
   yes
  </exclusive>
  <sporty>
   no
  </sporty>
 </clothing>
 <clothing>
  <id>
   840055175
  </id>
  <name>
   Adidas Shoes L-9081
  </name>
  <category>
   Shoes
  </category>
  <size>
   S
  </size>
  <color>
   Фиолетовый
  </color>
  <material>
   Вискоза
  </material>
  <price>
   619207
  </price>
  <rating>
   2.34
  </rating>
  <reviews>
   49252
  </reviews>
  <new>
   +
  </new>
  <sporty>
   yes
  </sporty>
 </clothing>
 <clothing>
  <id>
   493308544
  </id>
  <name>
   Converse Umbrellas U-4215
  </name>
  <category>
   Umbrellas
  </category>
  <size>
   L
  </size>
  <color>
   Красный
  </color>
  <material>
   Вискоза
  </material>
  <price>
   181078
  </price>
  <rating>
   1.99
  </rating>
  <reviews>
   172721
  </reviews>
  <new>
   +
  </new>
 </clothing>
 <clothing>
  <id>
   941889672
  </id>
  <name>
   Lacoste Shoes L-7164
  </name>
  <category>
   Shoes
  </category>
  <size>
   M
  </size>
  <color>
   Оранжевый
  </color>
  <material>
   Вискоза
  </material>
  <price>
   371867
  </price>
  <rating>
   1.42
  </rating>
  <reviews>
   548512
  </reviews>
  <new>
   +
  </new>
  <sporty>
   yes
  </sporty>
 </clothing>
 <clothing>
  <id>
   449351305
  </id>
  <name>
   Reebok Hat U-8277
  </name>
  <category>
   Hat
  </category>
  <size>
   L
  </size>
  <color>
   Красный
  </color>
  <material>
   Шелк
  </material>
  <price>
   109503
  </price>
  <rating>
   4.93
  </rating>
  <reviews>
   599832
  </reviews>
  <new>
   +
  </new>
  <sporty>
   yes
  </sporty>
 </clothing>
 <clothing>
  <id>
   261909870
  </id>
  <name>
   Asics Shirt U-7265
  </name>
  <category>
   Shirt
  </category>
  <size>
   S
  </size>
  <color>
   Оранжевый
  </color>
  <material>
   Нейлон
  </material>
  <price>
   461001
  </price>
  <rating>
   2.43
  </rating>
  <reviews>
   244233
  </reviews>
  <new>
   -
  </new>
  <exclusive>
   no
  </exclusive>
  <sporty>
   no
  </sporty>
 </clothing>
 <clothing>
  <id>
   316478094
  </id>
  <name>
   DC Dress Z-6878
  </name>
  <category>
   Dress
  </category>
  <size>
   M
  </size>
  <color>
   Красный
  </color>
  <material>
   Шерсть
  </material>
  <price>
   896914
  </price>
  <rating>
   1.89
  </rating>
  <reviews>
   775171
  </reviews>
  <new>
   -
  </new>
  <sporty>
   yes
  </sporty>
 </clothing>
 <clothing>
  <id>
   842604252
  </id>
  <name>
   Puma Blouse O-6386
  </name>
  <category>
   Blouse
  </category>
  <size>
   S
  </size>
  <color>
   Желтый
  </color>
  <material>
   Шерсть
  </material>
  <price>
   527956
  </price>
  <rating>
   2.67
  </rating>
  <reviews>
   33795
  </reviews>
 </clothing>
 <clothing>
  <id>
   856632249
  </id>
  <name>
   Converse Skirt E-3280
  </name>
  <category>
   Skirt
  </category>
  <size>
   L
  </size>
  <color>
   Голубой
  </color>
  <material>
   Лен
  </material>
  <price>
   809097
  </price>
  <rating>
   2.39
  </rating>
  <reviews>
   998974
  </reviews>
  <sporty>
   yes
  </sporty>
 </clothing>
 <clothing>
  <id>
   542509872
  </id>
  <name>
   Nike Gloves T-1710
  </name>
  <category>
   Gloves
  </category>
  <size>
   XL
  </size>
  <color>
   Оранжевый
  </color>
  <material>
   Вискоза
  </material>
  <price>
   703801
  </price>
  <rating>
   2.1
  </rating>
  <reviews>
   367527
  </reviews>
  <sporty>
   yes
  </sporty>
 </clothing>
 <clothing>
  <id>
   728806016
  </id>
  <name>
   PleinSport Dress R-3705
  </name>
  <category>
   Dress
  </category>
  <size>
   XXL
  </size>
  <color>
   Голубой
  </color>
  <material>
   Кожа
  </material>
  <price>
   527147
  </price>
  <rating>
   2.07
  </rating>
  <reviews>
   133547
  </reviews>
  <new>
   +
  </new>
  <exclusive>
   no
  </exclusive>
 </clothing>
 <clothing>
  <id>
   386388816
  </id>
  <name>
   Reebok Sweater O-5983
  </name>
  <category>
   Sweater
  </category>
  <size>
   L
  </size>
  <color>
   Синий
  </color>
  <material>
   Полиэстер
  </material>
  <price>
   424386
  </price>
  <rating>
   4.78
  </rating>
  <reviews>
   458351
  </reviews>
  <new>
   -
  </new>
 </clothing>
 <clothing>
  <id>
   915561615
  </id>
  <name>
   Lacoste Gloves B-5116
  </name>
  <category>
   Gloves
  </category>
  <size>
   XXL
  </size>
  <color>
   Синий
  </color>
  <material>
   Хлопок
  </material>
  <price>
   461514
  </price>
  <rating>
   3.14
  </rating>
  <reviews>
   957637
  </reviews>
  <new>
   -
  </new>
  <exclusive>
   yes
  </exclusive>
 </clothing>
 <clothing>
  <id>
   567662893
  </id>
  <name>
   Lacoste Belts E-7059
  </name>
  <category>
   Belts
  </category>
  <size>
   XL
  </size>
  <color>
   Красный
  </color>
  <material>
   Кожа
  </material>
  <price>
   871853
  </price>
  <rating>
   3.76
  </rating>
  <reviews>
   268398
  </reviews>
  <new>
   +
  </new>
  <sporty>
   no
  </sporty>
 </clothing>
 <clothing>
  <id>
   672078450
  </id>
  <name>
   Converse Belts X-9851
  </name>
  <category>
   Belts
  </category>
  <size>
   XL
  </size>
  <color>
   Красный
  </color>
  <material>
   Полиэстер
  </material>
  <price>
   346645
  </price>
  <rating>
   1.79
  </rating>
  <reviews>
   599913
  </reviews>
  <new>
   -
  </new>
  <exclusive>
   no
  </exclusive>
 </clothing>
 <clothing>
  <id>
   142450821
  </id>
  <name>
   Fila Umbrellas C-6650
  </name>
  <category>
   Umbrellas
  </category>
  <size>
   XL
  </size>
  <color>
   Синий
  </color>
  <material>
   Вискоза
  </material>
  <price>
   613183
  </price>
  <rating>
   4.75
  </rating>
  <reviews>
   670798
  </reviews>
  <new>
   -
  </new>
  <exclusive>
   no
  </exclusive>
 </clothing>
 <clothing>
  <id>
   414564258
  </id>
  <name>
   Brooks Dress L-5710
  </name>
  <category>
   Dress
  </category>
  <size>
   M
  </size>
  <color>
   Красный
  </color>
  <material>
   Кожа
  </material>
  <price>
   839095
  </price>
  <rating>
   4.95
  </rating>
  <reviews>
   974136
  </reviews>
  <new>
   +
  </new>
  <exclusive>
   no
  </exclusive>
  <sporty>
   yes
  </sporty>
 </clothing>
 <clothing>
  <id>
   587817755
  </id>
  <name>
   Ellesse T-shirt C-3801
  </name>
  <category>
   T-shirt
  </category>
  <size>
   S
  </size>
  <color>
   Желтый
  </color>
  <material>
   Полиэстер
  </material>
  <price>
   983185
  </price>
  <rating>
   2.16
  </rating>
  <reviews>
   374684
  </reviews>
  <exclusive>
   no
  </exclusive>
 </clothing>
 <clothing>
  <id>
   554819787
  </id>
  <name>
   Nike Blouse R-8420
  </name>
  <category>
   Blouse
  </category>
  <size>
   XXL
  </size>
  <color>
   Зеленый
  </color>
  <material>
   Шелк
  </material>
  <price>
   427870
  </price>
  <rating>
   4.37
  </rating>
  <reviews>
   830670
  </reviews>
  <exclusive>
   no
  </exclusive>
  <sporty>
   yes
  </sporty>
 </clothing>
 <clothing>
  <id>
   847926250
  </id>
  <name>
   Reebok Socks D-9409
  </name>
  <category>
   Socks
  </category>
  <size>
   M
  </size>
  <color>
   Зеленый
  </color>
  <material>
   Нейлон
  </material>
  <price>
   106721
  </price>
  <rating>
   4.54
  </rating>
  <reviews>
   135105
  </reviews>
  <sporty>
   no
  </sporty>
 </clothing>
 <clothing>
  <id>
   648386443
  </id>
  <name>
   Brooks Gloves T-2896
  </name>
  <category>
   Gloves
  </category>
  <size>
   L
  </size>
  <color>
   Красный
  </color>
  <material>
   Шерсть
  </material>
  <price>
   647167
  </price>
  <rating>
   2.63
  </rating>
  <reviews>
   979222
  </reviews>
  <sporty>
   yes
  </sporty>
 </clothing>
 <clothing>
  <id>
   582446551
  </id>
  <name>
   Puma Sweater F-9392
  </name>
  <category>
   Sweater
  </category>
  <size>
   S
  </size>
  <color>
   Желтый
  </color>
  <material>
   Лен
  </material>
  <price>
   921318
  </price>
  <rating>
   4.83
  </rating>
  <reviews>
   194071
  </reviews>
  <new>
   -
  </new>
  <sporty>
   yes
  </sporty>
 </clothing>
 <clothing>
  <id>
   451324105
  </id>
  <name>
   Asics Shirt R-9070
  </name>
  <category>
   Shirt
  </category>
  <size>
   S
  </size>
  <color>
   Голубой
  </color>
  <material>
   Полиэстер
  </material>
  <price>
   569308
  </price>
  <rating>
   3.55
  </rating>
  <reviews>
   160902
  </reviews>
  <new>
   +
  </new>
  <exclusive>
   yes
  </exclusive>
  <sporty>
   yes
  </sporty>
 </clothing>
 <clothing>
  <id>
   152431325
  </id>
  <name>
   Brooks Belts V-3184
  </name>
  <category>
   Belts
  </category>
  <size>
   S
  </size>
  <color>
   Оранжевый
  </color>
  <material>
   Шелк
  </material>
  <price>
   706193
  </price>
  <rating>
   2.84
  </rating>
  <reviews>
   570812
  </reviews>
  <new>
   +
  </new>
  <exclusive>
   no
  </exclusive>
  <sporty>
   no
  </sporty>
 </clothing>
 <clothing>
  <id>
   129959883
  </id>
  <name>
   Asics Blouse J-7133
  </name>
  <category>
   Blouse
  </category>
  <size>
   L
  </size>
  <color>
   Желтый
  </color>
  <material>
   Лен
  </material>
  <price>
   709461
  </price>
  <rating>
   4.5
  </rating>
  <reviews>
   97469
  </reviews>
  <new>
   -
  </new>
  <exclusive>
   yes
  </exclusive>
 </clothing>
 <clothing>
  <id>
   132528526
  </id>
  <name>
   Asics Dress X-5089
  </name>
  <category>
   Dress
  </category>
  <size>
   M
  </size>
  <color>
   Оранжевый
  </color>
  <material>
   Кожа
  </material>
  <price>
   279353
  </price>
  <rating>
   3.45
  </rating>
  <reviews>
   725922
  </reviews>
  <exclusive>
   yes
  </exclusive>
 </clothing>
 <clothing>
  <id>
   120798242
  </id>
  <name>
   Ellesse Sweater V-9773
  </name>
  <category>
   Sweater
  </category>
  <size>
   XL
  </size>
  <color>
   Оранжевый
  </color>
  <material>
   Нейлон
  </material>
  <price>
   501878
  </price>
  <rating>
   1.84
  </rating>
  <reviews>
   19537
  </reviews>
  <exclusive>
   yes
  </exclusive>
 </clothing>
 <clothing>
  <id>
   527571422
  </id>
  <name>
   Under Armour Jeans O-9500
  </name>
  <category>
   Jeans
  </category>
  <size>
   L
  </size>
  <color>
   Синий
  </color>
  <material>
   Нейлон
  </material>
  <price>
   488727
  </price>
  <rating>
   1.96
  </rating>
  <reviews>
   643796
  </reviews>
  <new>
   +
  </new>
  <exclusive>
   no
  </exclusive>
  <sporty>
   yes
  </sporty>
 </clothing>
 <clothing>
  <id>
   138043634
  </id>
  <name>
   New Balance T-shirt T-7807
  </name>
  <category>
   T-shirt
  </category>
  <size>
   M
  </size>
  <color>
   Оранжевый
  </color>
  <material>
   Лен
  </material>
  <price>
   724983
  </price>
  <rating>
   3.36
  </rating>
  <reviews>
   833172
  </reviews>
 </clothing>
 <clothing>
  <id>
   656432354
  </id>
  <name>
   Brooks Jacket I-3234
  </name>
  <category>
   Jacket
  </category>
  <size>
   XXL
  </size>
  <color>
   Оранжевый
  </color>
  <material>
   Вискоза
  </material>
  <price>
   685823
  </price>
  <rating>
   1.56
  </rating>
  <reviews>
   625716
  </reviews>
  <new>
   -
  </new>
 </clothing>
 <clothing>
  <id>
   761721259
  </id>
  <name>
   Under Armour Jeans C-6343
  </name>
  <category>
   Jeans
  </category>
  <size>
   XL
  </size>
  <color>
   Зеленый
  </color>
  <material>
   Шелк
  </material>
  <price>
   157211
  </price>
  <rating>
   3.83
  </rating>
  <reviews>
   423594
  </reviews>
 </clothing>
 <clothing>
  <id>
   790265532
  </id>
  <name>
   New Balance Shirt L-6449
  </name>
  <category>
   Shirt
  </category>
  <size>
   M
  </size>
  <color>
   Голубой
  </color>
  <material>
   Шелк
  </material>
  <price>
   823342
  </price>
  <rating>
   3.97
  </rating>
  <reviews>
   962439
  </reviews>
  <sporty>
   no
  </sporty>
 </clothing>
 <clothing>
  <id>
   120686022
  </id>
  <name>
   DC T-shirt F-9000
  </name>
  <category>
   T-shirt
  </category>
  <size>
   XXL
  </size>
  <color>
   Синий
  </color>
  <material>
   Лен
  </material>
  <price>
   540571
  </price>
  <rating>
   1.29
  </rating>
  <reviews>
   547634
  </reviews>
  <sporty>
   no
  </sporty>
 </clothing>
 <clothing>
  <id>
   820954958
  </id>
  <name>
   Vans Socks A-8883
  </name>
  <category>
   Socks
  </category>
  <size>
   L
  </size>
  <color>
   Красный
  </color>
  <material>
   Лен
  </material>
  <price>
   457428
  </price>
  <rating>
   1.69
  </rating>
  <reviews>
   651992
  </reviews>
  <new>
   -
  </new>
  <sporty>
   no
  </sporty>
 </clothing>
 <clothing>
  <id>
   418620694
  </id>
  <name>
   Addidas Handbags N-8072
  </name>
  <category>
   Handbags
  </category>
  <size>
   XL
  </size>
  <color>
   Синий
  </color>
  <material>
   Хлопок
  </material>
  <price>
   708040
  </price>
  <rating>
   1.9
  </rating>
  <reviews>
   528103
  </reviews>
  <exclusive>
   yes
  </exclusive>
 </clothing>
 <clothing>
  <id>
   568756841
  </id>
  <name>
   Converse T-shirt F-6655
  </name>
  <category>
   T-shirt
  </category>
  <size>
   M
  </size>
  <color>
   Зеленый
  </color>
  <material>
   Лен
  </material>
  <price>
   594363
  </price>
  <rating>
   4.6
  </rating>
  <reviews>
   95950
  </reviews>
 </clothing>
 <clothing>
  <id>
   785336802
  </id>
  <name>
   DC Sweater N-7633
  </name>
  <category>
   Sweater
  </category>
  <size>
   L
  </size>
  <color>
   Фиолетовый
  </color>
  <material>
   Лен
  </material>
  <price>
   459915
  </price>
  <rating>
   4.43
  </rating>
  <reviews>
   415115
  </reviews>
  <new>
   -
  </new>
  <exclusive>
   no
  </exclusive>
 </clothing>
 <clothing>
  <id>
   293488991
  </id>
  <name>
   PleinSport Umbrellas W-7621
  </name>
  <category>
   Umbrellas
  </category>
  <size>
   M
  </size>
  <color>
   Красный
  </color>
  <material>
   Вискоза
  </material>
  <price>
   835854
  </price>
  <rating>
   1.88
  </rating>
  <reviews>
   141905
  </reviews>
  <new>
   -
  </new>
  <sporty>
   yes
  </sporty>
 </clothing>
 <clothing>
  <id>
   842957538
  </id>
  <name>
   PleinSport Socks M-7882
  </name>
  <category>
   Socks
  </category>
  <size>
   M
  </size>
  <color>
   Желтый
  </color>
  <material>
   Вискоза
  </material>
  <price>
   188898
  </price>
  <rating>
   2.09
  </rating>
  <reviews>
   1460
  </reviews>
  <exclusive>
   no
  </exclusive>
  <sporty>
   no
  </sporty>
 </clothing>
</clothing-items>
